hilbert.cpython-310-darwin.so
cyhilbert/__init__.py
cyhilbert/__init__.pyi
cyhilbert/py.typed
cyhilbert-1.3.1.dist-info/LICENSE
cyhilbert-1.3.1.dist-info/METADATA
cyhilbert-1.3.1.dist-info/WHEEL
cyhilbert-1.3.1.dist-info/top_level.txt
cyhilbert-1.3.1.dist-info/RECORD
