Metadata-Version: 2.1
Name: cyhilbert
Version: 1.3.1
Summary: A cythonized version of that one hilbert function you keep copy-pasting.
Home-page: https://github.com/invisiblefunnel/cyhilbert
Author: Danny Whalen
Author-email: daniel.r.whalen@gmail.com
License: MIT
Classifier: Programming Language :: Python :: 3
Classifier: License :: OSI Approved :: MIT License
Classifier: Operating System :: OS Independent
Requires-Python: >=3
License-File: LICENSE
Provides-Extra: tests
Requires-Dist: mypy ; extra == 'tests'
Requires-Dist: hilbertcurve ; extra == 'tests'
